geoips/__init__.py
geoips/_version.py
geoips/cli.py
geoips/commandline/__init__.py
geoips/commandline/ancillary_info/__init__.py
geoips/commandline/ancillary_info/alias_mapping.yaml
geoips/commandline/ancillary_info/cmd_instructions.yaml
geoips/commandline/ancillary_info/test-data-urls.yaml
geoips/commandline/ancillary_info/test_data.py
geoips/commandline/args.py
geoips/commandline/cmd_instructions.py
geoips/commandline/commandline_interface.py
geoips/commandline/geoips_command.py
geoips/commandline/geoips_config.py
geoips/commandline/geoips_describe.py
geoips/commandline/geoips_list.py
geoips/commandline/geoips_run.py
geoips/commandline/geoips_test.py
geoips/commandline/geoips_tree.py
geoips/commandline/geoips_validate.py
geoips/commandline/list_available_plugins.py
geoips/commandline/log_setup.py
geoips/commandline/run_procflow.py
geoips/commandline/update_tc_tracks_database.py
geoips/create_plugin_registries.py
geoips/data_manipulations/__init__.py
geoips/data_manipulations/conversions.py
geoips/data_manipulations/corrections.py
geoips/data_manipulations/info.py
geoips/data_manipulations/merge.py
geoips/dev/__init__.py
geoips/dev/output_config.py
geoips/dev/product.py
geoips/errors.py
geoips/filenames/__init__.py
geoips/filenames/base_paths.py
geoips/filenames/duplicate_files.py
geoips/geoips_utils.py
geoips/image_utils/__init__.py
geoips/image_utils/colormap_utils.py
geoips/image_utils/maps.py
geoips/image_utils/mpl_utils.py
geoips/interfaces/__init__.py
geoips/interfaces/base.py
geoips/interfaces/module_based/__init__.py
geoips/interfaces/module_based/algorithms.py
geoips/interfaces/module_based/colormappers.py
geoips/interfaces/module_based/coverage_checkers.py
geoips/interfaces/module_based/databases.py
geoips/interfaces/module_based/filename_formatters.py
geoips/interfaces/module_based/interpolators.py
geoips/interfaces/module_based/output_checkers.py
geoips/interfaces/module_based/output_formatters.py
geoips/interfaces/module_based/procflows.py
geoips-1.16.3.dist-info/LICENSE
geoips-1.16.3.dist-info/METADATA
geoips-1.16.3.dist-info/WHEEL
geoips-1.16.3.dist-info/entry_points.txt
geoips-1.16.3.dist-info/RECORD
