Metadata-Version: 2.3
Name: geoips
Version: 1.16.3
Summary: Geolocated Information Processing System
Keywords: GeoIPS,Poetry
Author: GeoIPS
Author-email: geoips@nrlmry.navy.mil
Maintainer: GeoIPS
Maintainer-email: geoips@nrlmry.navy.mil
Requires-Python: >=3.11.0,<3.13.0
Classifier: Programming Language :: Python :: 3
Classifier: Programming Language :: Python :: 3.11
Classifier: Programming Language :: Python :: 3.12
Provides-Extra: debug
Provides-Extra: doc
Provides-Extra: lint
Provides-Extra: test
Requires-Dist: alphashape (>=1.3.1)
Requires-Dist: astropy
Requires-Dist: bandit ; extra == "lint"
Requires-Dist: black ; extra == "lint"
Requires-Dist: brassy (>=0.0.3) ; extra == "doc"
Requires-Dist: cartopy (>=0.23.0)
Requires-Dist: colorama
Requires-Dist: doc8 ; extra == "lint"
Requires-Dist: ephem
Requires-Dist: flake8 ; extra == "lint"
Requires-Dist: flake8-docstrings ; extra == "lint"
Requires-Dist: flake8-rst ; extra == "lint"
Requires-Dist: flake8-rst-docstrings ; extra == "lint"
Requires-Dist: h5py
Requires-Dist: hdf5plugin
Requires-Dist: ipython ; extra == "debug"
Requires-Dist: isodate
Requires-Dist: jsonschema (>4.18.0)
Requires-Dist: m2r2 ; extra == "doc"
Requires-Dist: matplotlib (>=3.7.0)
Requires-Dist: mistune (==0.8.4) ; extra == "doc"
Requires-Dist: netcdf4 (>1.7.0)
Requires-Dist: numexpr
Requires-Dist: numpy (>=2.2.4,<2.3.0)
Requires-Dist: pinkrst ; extra == "lint"
Requires-Dist: pixelmatch ; extra == "test"
Requires-Dist: prettier ; extra == "lint"
Requires-Dist: psutil
Requires-Dist: pyaml-env
Requires-Dist: pydantic (>=2.10.0)
Requires-Dist: pydata-sphinx-theme ; extra == "doc"
Requires-Dist: pygrib
Requires-Dist: pyhdf
Requires-Dist: pylint ; extra == "lint"
Requires-Dist: pyorbital
Requires-Dist: pypublicdecompwt
Requires-Dist: pyresample
Requires-Dist: pytest ; extra == "test"
Requires-Dist: pytest-cov ; extra == "test"
Requires-Dist: pytest-mock (>=3.14.0) ; extra == "test"
Requires-Dist: pytest-xdist ; extra == "test"
Requires-Dist: pyyaml
Requires-Dist: rasterio
Requires-Dist: referencing
Requires-Dist: rich ; extra == "doc"
Requires-Dist: rich-argparse ; extra == "doc"
Requires-Dist: rio-cogeo
Requires-Dist: satpy
Requires-Dist: scikit-image
Requires-Dist: scipy (>1.2)
Requires-Dist: setuptools (<70)
Requires-Dist: sphinx (<7.2) ; extra == "doc"
Requires-Dist: sphinx-argparse ; extra == "doc"
Requires-Dist: sphinx-design ; extra == "doc"
Requires-Dist: sphinxcontrib-autoprogram ; extra == "doc"
Requires-Dist: sphinxcontrib-mermaid ; extra == "doc"
Requires-Dist: tabulate
Requires-Dist: tqdm
Requires-Dist: xarray (>=2025.3.1)
Project-URL: Repository, https://github.com/NRLMMD-GEOIPS/geoips
